{
  "classes": [
    {
      "label": "Outcome",
      "definition": null,
      "synonyms": [],
      "provenance": [
        "The BrainIT group concept and core dataset definition::chunk-0",
        "The BrainIT group concept and core dataset definition::chunk-1",
        "The BrainIT group concept and core dataset definition::chunk-12",
        "The BrainIT group concept and core dataset definition::chunk-13",
        "symbolic_reasoner_dedupe"
      ],
      "stratum": "core",
      "original_label": null,
      "evidence": "missed secondary insults could potentially adversely influence outcome",
      "aliases": [
        "outcome"
      ]
    },
    {
      "label": "Monitoring Data",
      "definition": null,
      "synonyms": [],
      "provenance": [
        "The BrainIT group concept and core dataset definition::chunk-0",
        "The BrainIT group concept and core dataset definition::chunk-1",
        "The BrainIT group concept and core dataset definition::chunk-6",
        "The BrainIT group concept and core dataset definition::chunk-13",
        "symbolic_reasoner_dedupe"
      ],
      "stratum": "core",
      "original_label": null,
      "evidence": "more detailed collection of admission, monitoring, treatment and outcome data from patients with brain injury",
      "aliases": []
    },
    {
      "label": "Cerebral Perfusion Pressure (CPP)",
      "definition": null,
      "synonyms": [],
      "provenance": [
        "The BrainIT group concept and core dataset definition::chunk-1",
        "The BrainIT group concept and core dataset definition::chunk-8",
        "The BrainIT group concept and core dataset definition::chunk-15",
        "symbolic_reasoner_dedupe",
        "schema_guided_completion"
      ],
      "stratum": "core",
      "original_label": null,
      "evidence": "Cerebral perfusion pressure (CPP 1/4 BP-ICP) monitoring is a good example.",
      "aliases": [
        "Cerebral Perfusion Pressure (CPP)",
        "CPP"
      ]
    },
    {
      "label": "Intracranial Pressure (ICP)",
      "definition": null,
      "synonyms": [],
      "provenance": [
        "The BrainIT group concept and core dataset definition::chunk-1",
        "The BrainIT group concept and core dataset definition::chunk-5",
        "The BrainIT group concept and core dataset definition::chunk-6",
        "The BrainIT group concept and core dataset definition::chunk-15",
        "symbolic_reasoner_dedupe",
        "schema_guided_completion"
      ],
      "stratum": "core",
      "original_label": null,
      "evidence": "Time of BP, ICP and central venous pressure (CVP) monitoring is also indicated",
      "aliases": [
        "Intracranial Pressure (ICP)",
        "Intracranial Pressure",
        "ICP"
      ]
    },
    {
      "label": "Patient",
      "definition": null,
      "synonyms": [],
      "provenance": [
        "The BrainIT group concept and core dataset definition::chunk-1",
        "The BrainIT group concept and core dataset definition::chunk-6",
        "The BrainIT group concept and core dataset definition::chunk-13",
        "Trusting-Intensive-Care-Unit-::chunk-1",
        "symbolic_reasoner_dedupe"
      ],
      "stratum": "core",
      "original_label": null,
      "evidence": "data collection of admission, monitoring, treatment and outcome data from patients with brain injury",
      "aliases": []
    },
    {
      "label": "Ventilation",
      "definition": null,
      "synonyms": [],
      "provenance": [
        "The BrainIT group concept and core dataset definition::chunk-5",
        "The BrainIT group concept and core dataset definition::chunk-8",
        "symbolic_reasoner_dedupe"
      ],
      "stratum": "core",
      "original_label": null,
      "evidence": "the patient was on ventilation from 22:40 to end of the time period",
      "aliases": []
    },
    {
      "label": "Sedation",
      "definition": null,
      "synonyms": [],
      "provenance": [
        "The BrainIT group concept and core dataset definition::chunk-5",
        "The BrainIT group concept and core dataset definition::chunk-8",
        "symbolic_reasoner_dedupe"
      ],
      "stratum": "core",
      "original_label": null,
      "evidence": "was sedated from 22:00 to 03:50, and again from 04:10 to the end of the period",
      "aliases": []
    },
    {
      "label": "CVP",
      "definition": null,
      "synonyms": [],
      "provenance": [
        "The BrainIT group concept and core dataset definition::chunk-5",
        "The BrainIT group concept and core dataset definition::chunk-7",
        "symbolic_reasoner_dedupe"
      ],
      "stratum": "core",
      "original_label": null,
      "evidence": "Time of BP, ICP and central venous pressure (CVP) monitoring is also indicated",
      "aliases": [
        "Central Venous Pressure (CVP)"
      ]
    },
    {
      "label": "Secondary Insult Treatment",
      "definition": null,
      "synonyms": [],
      "provenance": [
        "The BrainIT group concept and core dataset definition::chunk-5",
        "symbolic_reasoner_dedupe"
      ],
      "stratum": "core",
      "original_label": null,
      "evidence": "Secondary insult treatment information",
      "aliases": []
    },
    {
      "label": "GCS Assessment",
      "definition": null,
      "synonyms": [],
      "provenance": [
        "The BrainIT group concept and core dataset definition::chunk-7",
        "symbolic_reasoner_dedupe"
      ],
      "stratum": "core",
      "original_label": null,
      "evidence": "the clinical status of the patient (e.g.: GCS scores)",
      "aliases": []
    },
    {
      "label": "CT Scan Assessment",
      "definition": null,
      "synonyms": [],
      "provenance": [
        "The BrainIT group concept and core dataset definition::chunk-7",
        "symbolic_reasoner_dedupe"
      ],
      "stratum": "core",
      "original_label": null,
      "evidence": "CT-Scan data",
      "aliases": []
    },
    {
      "label": "GOSe Outcome",
      "definition": null,
      "synonyms": [],
      "provenance": [
        "The BrainIT group concept and core dataset definition::chunk-7",
        "symbolic_reasoner_dedupe"
      ],
      "stratum": "core",
      "original_label": null,
      "evidence": "the Extended 8point Glasgow Outcome Scale (GOSe) at 6 months post discharge",
      "aliases": []
    },
    {
      "label": "Heart Rate",
      "definition": null,
      "synonyms": [],
      "provenance": [
        "The BrainIT group concept and core dataset definition::chunk-7",
        "symbolic_reasoner_dedupe"
      ],
      "stratum": "core",
      "original_label": null,
      "evidence": "Minute by minute monitoring data... Heart Rate (specifying source: ECG or Pulse Oximetry)",
      "aliases": []
    },
    {
      "label": "Respiration Rate",
      "definition": null,
      "synonyms": [],
      "provenance": [
        "The BrainIT group concept and core dataset definition::chunk-7",
        "symbolic_reasoner_dedupe"
      ],
      "stratum": "core",
      "original_label": null,
      "evidence": "Respiration Rate (sources: impedance plethmography or ventilator)",
      "aliases": []
    },
    {
      "label": "Mean Arterial Pressure (MAP)",
      "definition": null,
      "synonyms": [],
      "provenance": [
        "The BrainIT group concept and core dataset definition::chunk-7",
        "symbolic_reasoner_dedupe"
      ],
      "stratum": "core",
      "original_label": null,
      "evidence": "Mean Arterial Pressure",
      "aliases": [
        "Mean Arterial Pressure"
      ]
    },
    {
      "label": "SaO2",
      "definition": null,
      "synonyms": [],
      "provenance": [
        "The BrainIT group concept and core dataset definition::chunk-7",
        "symbolic_reasoner_dedupe"
      ],
      "stratum": "core",
      "original_label": null,
      "evidence": "Pulse Oximetry (SaO2)",
      "aliases": []
    },
    {
      "label": "Temperature",
      "definition": null,
      "synonyms": [],
      "provenance": [
        "The BrainIT group concept and core dataset definition::chunk-7",
        "symbolic_reasoner_dedupe"
      ],
      "stratum": "core",
      "original_label": null,
      "evidence": "Temperature (sources: rectal=oesophageal= bladder=skin)",
      "aliases": []
    },
    {
      "label": "Brain Temperature",
      "definition": null,
      "synonyms": [],
      "provenance": [
        "The BrainIT group concept and core dataset definition::chunk-7",
        "symbolic_reasoner_dedupe"
      ],
      "stratum": "core",
      "original_label": null,
      "evidence": "Brain Temperature",
      "aliases": []
    },
    {
      "label": "Microdialysis",
      "definition": null,
      "synonyms": [],
      "provenance": [
        "The BrainIT group concept and core dataset definition::chunk-7",
        "The BrainIT group concept and core dataset definition::chunk-9",
        "symbolic_reasoner_dedupe"
      ],
      "stratum": "core",
      "original_label": null,
      "evidence": "the BrainIT group is collaborating with three medical device companies (Philips Medical, CMA Microdialysis and Licox)",
      "aliases": []
    },
    {
      "label": "Pupil Assessment",
      "definition": null,
      "synonyms": [],
      "provenance": [
        "The BrainIT group concept and core dataset definition::chunk-8",
        "symbolic_reasoner_dedupe"
      ],
      "stratum": "core",
      "original_label": null,
      "evidence": "pupil scores",
      "aliases": []
    },
    {
      "label": "Fluids",
      "definition": null,
      "synonyms": [],
      "provenance": [
        "The BrainIT group concept and core dataset definition::chunk-8",
        "symbolic_reasoner_dedupe"
      ],
      "stratum": "core",
      "original_label": null,
      "evidence": "fluid input and output",
      "aliases": []
    },
    {
      "label": "Vasopressors",
      "definition": null,
      "synonyms": [],
      "provenance": [
        "The BrainIT group concept and core dataset definition::chunk-8",
        "symbolic_reasoner_dedupe"
      ],
      "stratum": "core",
      "original_label": null,
      "evidence": "use of vasopressors",
      "aliases": []
    },
    {
      "label": "Biochemistry",
      "definition": null,
      "synonyms": [],
      "provenance": [
        "The BrainIT group concept and core dataset definition::chunk-8",
        "symbolic_reasoner_dedupe"
      ],
      "stratum": "core",
      "original_label": null,
      "evidence": "Biochemistry (Na, K \u00fe , Glucose)",
      "aliases": []
    },
    {
      "label": "Haematology",
      "definition": null,
      "synonyms": [],
      "provenance": [
        "The BrainIT group concept and core dataset definition::chunk-8",
        "symbolic_reasoner_dedupe"
      ],
      "stratum": "core",
      "original_label": null,
      "evidence": "Haematology (Haemaglobin, White Cell Count, Haematocrit)",
      "aliases": []
    },
    {
      "label": "Secondary Insult",
      "definition": null,
      "synonyms": [],
      "provenance": [
        "The BrainIT group concept and core dataset definition::chunk-8",
        "The BrainIT group concept and core dataset definition::chunk-12",
        "The BrainIT group concept and core dataset definition::chunk-15",
        "symbolic_reasoner_dedupe"
      ],
      "stratum": "core",
      "original_label": null,
      "evidence": "large numbers of secondary insults could be missed",
      "aliases": [
        "secondary insult"
      ]
    },
    {
      "label": "Arterial Pressors",
      "definition": null,
      "synonyms": [],
      "provenance": [
        "The BrainIT group concept and core dataset definition::chunk-8",
        "symbolic_reasoner_dedupe"
      ],
      "stratum": "core",
      "original_label": null,
      "evidence": "arterial pressors",
      "aliases": []
    },
    {
      "label": "Systemic Hypotension",
      "definition": null,
      "synonyms": [],
      "provenance": [
        "The BrainIT group concept and core dataset definition::chunk-8",
        "symbolic_reasoner_dedupe"
      ],
      "stratum": "core",
      "original_label": null,
      "evidence": "systemic hypotension",
      "aliases": []
    },
    {
      "label": "Jugular Venous Desaturation",
      "definition": null,
      "synonyms": [],
      "provenance": [
        "The BrainIT group concept and core dataset definition::chunk-11",
        "symbolic_reasoner_dedupe"
      ],
      "stratum": "core",
      "original_label": null,
      "evidence": "increased the incidence of jugular venous desaturations",
      "aliases": []
    },
    {
      "label": "Intracranial Hypertension",
      "definition": null,
      "synonyms": [],
      "provenance": [
        "The BrainIT group concept and core dataset definition::chunk-11",
        "symbolic_reasoner_dedupe"
      ],
      "stratum": "core",
      "original_label": null,
      "evidence": "secondary insults such as intracranial hypertension",
      "aliases": []
    },
    {
      "label": "Arterial Hypotension",
      "definition": null,
      "synonyms": [],
      "provenance": [
        "The BrainIT group concept and core dataset definition::chunk-11",
        "symbolic_reasoner_dedupe"
      ],
      "stratum": "core",
      "original_label": null,
      "evidence": "secondary insults such as arterial hypotension",
      "aliases": []
    },
    {
      "label": "Acute Respiratory Distress Syndrome",
      "definition": null,
      "synonyms": [],
      "provenance": [
        "The BrainIT group concept and core dataset definition::chunk-11",
        "symbolic_reasoner_dedupe"
      ],
      "stratum": "core",
      "original_label": null,
      "evidence": "increased the incidence of acute respiratory distress syndrome",
      "aliases": []
    },
    {
      "label": "Condition",
      "definition": null,
      "synonyms": [],
      "provenance": [
        "The BrainIT group concept and core dataset definition::chunk-13",
        "symbolic_reasoner_dedupe"
      ],
      "stratum": "core",
      "original_label": null,
      "evidence": "management of patients with brain injury",
      "aliases": []
    },
    {
      "label": "Hypotension",
      "definition": null,
      "synonyms": [],
      "provenance": [
        "The BrainIT group concept and core dataset definition::chunk-15",
        "Trusting-Intensive-Care-Unit-::chunk-2",
        "symbolic_reasoner_dedupe"
      ],
      "stratum": "core",
      "original_label": null,
      "evidence": "Impact of ICP instability and hypotension on outcome in patients with severe head trauma",
      "aliases": []
    },
    {
      "label": "Sepsis",
      "definition": null,
      "synonyms": [],
      "provenance": [
        "Trusting-Intensive-Care-Unit-::chunk-0",
        "symbolic_reasoner_dedupe"
      ],
      "stratum": "core",
      "original_label": null,
      "evidence": "if the patient was suffering from sepsis at the same time",
      "aliases": []
    },
    {
      "label": "Timepoint",
      "definition": null,
      "synonyms": [],
      "provenance": [
        "Trusting-Intensive-Care-Unit-::chunk-1",
        "symbolic_reasoner_dedupe"
      ],
      "stratum": "core",
      "original_label": null,
      "evidence": "pd:Timepoint as a subclass of mo:ObservationCollection",
      "aliases": []
    },
    {
      "label": "Observation",
      "definition": null,
      "synonyms": [],
      "provenance": [
        "Trusting-Intensive-Care-Unit-::chunk-1",
        "symbolic_reasoner_dedupe"
      ],
      "stratum": "core",
      "original_label": null,
      "evidence": "defining pd:Timepoint as a subclass of mo:ObservationCollection, which has an associated set of ssn:Observations.",
      "aliases": []
    },
    {
      "label": "Parameter",
      "definition": null,
      "synonyms": [],
      "provenance": [
        "Trusting-Intensive-Care-Unit-::chunk-1",
        "symbolic_reasoner_dedupe"
      ],
      "stratum": "core",
      "original_label": null,
      "evidence": "pd:Parameter (representing things that were recorded) as a subclass of ssn:Property",
      "aliases": []
    },
    {
      "label": "Possible Error",
      "definition": null,
      "synonyms": [],
      "provenance": [
        "Trusting-Intensive-Care-Unit-::chunk-1",
        "symbolic_reasoner_dedupe"
      ],
      "stratum": "core",
      "original_label": null,
      "evidence": "identified as an error it is annotated with 'Possible Error' (PoE)",
      "aliases": []
    },
    {
      "label": "Probable Error",
      "definition": null,
      "synonyms": [],
      "provenance": [
        "Trusting-Intensive-Care-Unit-::chunk-1",
        "symbolic_reasoner_dedupe"
      ],
      "stratum": "core",
      "original_label": null,
      "evidence": "annotated with 'Possible Error' (PoE) or a 'Probable Error' (PrE); where PrE is more likely to be an error than PoE.",
      "aliases": []
    },
    {
      "label": "Hypertension",
      "definition": null,
      "synonyms": [],
      "provenance": [
        "Trusting-Intensive-Care-Unit-::chunk-2",
        "symbolic_reasoner_dedupe"
      ],
      "stratum": "core",
      "original_label": null,
      "evidence": "affected by hypertension (91%)",
      "aliases": []
    },
    {
      "label": "Noradrenaline",
      "definition": null,
      "synonyms": [],
      "provenance": [
        "Trusting-Intensive-Care-Unit-::chunk-2",
        "symbolic_reasoner_dedupe"
      ],
      "stratum": "core",
      "original_label": null,
      "evidence": "noradrenaline (24.2%)",
      "aliases": []
    },
    {
      "label": "Adrenaline",
      "definition": null,
      "synonyms": [],
      "provenance": [
        "Trusting-Intensive-Care-Unit-::chunk-2",
        "symbolic_reasoner_dedupe"
      ],
      "stratum": "core",
      "original_label": null,
      "evidence": "adrenaline (6.7%)",
      "aliases": []
    },
    {
      "label": "Session",
      "definition": null,
      "synonyms": [],
      "provenance": [
        "schema_guided_completion",
        "symbolic_reasoner_dedupe"
      ],
      "stratum": "schema_guided",
      "original_label": null,
      "evidence": "a continuous monitoring session for a patient in the ICU",
      "aliases": []
    },
    {
      "label": "Core Monitoring Parameter",
      "definition": null,
      "synonyms": [],
      "provenance": [
        "schema_guided_completion",
        "symbolic_reasoner_dedupe"
      ],
      "stratum": "schema_guided",
      "original_label": null,
      "evidence": "minimum required minute-by-minute monitoring parameters",
      "aliases": []
    },
    {
      "label": "Optional Monitoring Parameter",
      "definition": null,
      "synonyms": [],
      "provenance": [
        "schema_guided_completion",
        "symbolic_reasoner_dedupe"
      ],
      "stratum": "schema_guided",
      "original_label": null,
      "evidence": "extended monitoring parameters included in the BrainIT Database",
      "aliases": []
    },
    {
      "label": "Derived Parameter",
      "definition": null,
      "synonyms": [],
      "provenance": [
        "schema_guided_completion",
        "symbolic_reasoner_dedupe"
      ],
      "stratum": "schema_guided",
      "original_label": null,
      "evidence": "monitoring parameter computed from other measured parameters",
      "aliases": []
    },
    {
      "label": "EtCO2",
      "definition": null,
      "synonyms": [],
      "provenance": [
        "schema_guided_completion",
        "symbolic_reasoner_dedupe"
      ],
      "stratum": "schema_guided",
      "original_label": null,
      "evidence": "EtCO2",
      "aliases": []
    },
    {
      "label": "SjO2",
      "definition": null,
      "synonyms": [],
      "provenance": [
        "schema_guided_completion",
        "symbolic_reasoner_dedupe"
      ],
      "stratum": "schema_guided",
      "original_label": null,
      "evidence": "SjO2",
      "aliases": []
    },
    {
      "label": "TCD",
      "definition": null,
      "synonyms": [],
      "provenance": [
        "schema_guided_completion",
        "symbolic_reasoner_dedupe"
      ],
      "stratum": "schema_guided",
      "original_label": null,
      "evidence": "TCD",
      "aliases": []
    },
    {
      "label": "PbrO2",
      "definition": null,
      "synonyms": [],
      "provenance": [
        "schema_guided_completion",
        "symbolic_reasoner_dedupe"
      ],
      "stratum": "schema_guided",
      "original_label": null,
      "evidence": "PbrO2",
      "aliases": []
    },
    {
      "label": "Baseline Therapy",
      "definition": null,
      "synonyms": [],
      "provenance": [
        "schema_guided_completion",
        "symbolic_reasoner_dedupe"
      ],
      "stratum": "schema_guided",
      "original_label": null,
      "evidence": "Routine ICU management delivered to all TBI patients",
      "aliases": []
    },
    {
      "label": "Secondary Insult Therapy",
      "definition": null,
      "synonyms": [],
      "provenance": [
        "schema_guided_completion",
        "symbolic_reasoner_dedupe"
      ],
      "stratum": "schema_guided",
      "original_label": null,
      "evidence": "medical management=therapy given to patients specifically to treat secondary insults",
      "aliases": []
    },
    {
      "label": "Nutrition",
      "definition": null,
      "synonyms": [],
      "provenance": [
        "schema_guided_completion",
        "symbolic_reasoner_dedupe"
      ],
      "stratum": "schema_guided",
      "original_label": null,
      "evidence": "nutrition",
      "aliases": []
    },
    {
      "label": "Antibiotics",
      "definition": null,
      "synonyms": [],
      "provenance": [
        "schema_guided_completion",
        "symbolic_reasoner_dedupe"
      ],
      "stratum": "schema_guided",
      "original_label": null,
      "evidence": "antibiotics",
      "aliases": []
    },
    {
      "label": "Clinical Assessment",
      "definition": null,
      "synonyms": [],
      "provenance": [
        "schema_guided_completion",
        "symbolic_reasoner_dedupe"
      ],
      "stratum": "schema_guided",
      "original_label": null,
      "evidence": "structured clinical evaluation performed at admission",
      "aliases": []
    },
    {
      "label": "Laboratory Values",
      "definition": null,
      "synonyms": [],
      "provenance": [
        "schema_guided_completion",
        "symbolic_reasoner_dedupe"
      ],
      "stratum": "schema_guided",
      "original_label": null,
      "evidence": "Routine laboratory tests performed during ICU management",
      "aliases": []
    },
    {
      "label": "Blood Gases",
      "definition": null,
      "synonyms": [],
      "provenance": [
        "schema_guided_completion",
        "symbolic_reasoner_dedupe"
      ],
      "stratum": "schema_guided",
      "original_label": null,
      "evidence": "Arterial blood gas analysis",
      "aliases": []
    },
    {
      "label": "Sodium",
      "definition": null,
      "synonyms": [],
      "provenance": [
        "schema_guided_completion",
        "symbolic_reasoner_dedupe"
      ],
      "stratum": "schema_guided",
      "original_label": null,
      "evidence": "Serum sodium (Na)",
      "aliases": []
    },
    {
      "label": "Potassium",
      "definition": null,
      "synonyms": [],
      "provenance": [
        "schema_guided_completion",
        "symbolic_reasoner_dedupe"
      ],
      "stratum": "schema_guided",
      "original_label": null,
      "evidence": "Serum potassium (K+)",
      "aliases": []
    },
    {
      "label": "Glucose",
      "definition": null,
      "synonyms": [],
      "provenance": [
        "schema_guided_completion",
        "symbolic_reasoner_dedupe"
      ],
      "stratum": "schema_guided",
      "original_label": null,
      "evidence": "Blood glucose",
      "aliases": []
    },
    {
      "label": "Haemoglobin",
      "definition": null,
      "synonyms": [],
      "provenance": [
        "schema_guided_completion",
        "symbolic_reasoner_dedupe"
      ],
      "stratum": "schema_guided",
      "original_label": null,
      "evidence": "Haemoglobin concentration",
      "aliases": []
    },
    {
      "label": "White Blood Cell Count",
      "definition": null,
      "synonyms": [],
      "provenance": [
        "schema_guided_completion",
        "symbolic_reasoner_dedupe"
      ],
      "stratum": "schema_guided",
      "original_label": null,
      "evidence": "White cell count (WBC)",
      "aliases": []
    },
    {
      "label": "Haematocrit",
      "definition": null,
      "synonyms": [],
      "provenance": [
        "schema_guided_completion",
        "symbolic_reasoner_dedupe"
      ],
      "stratum": "schema_guided",
      "original_label": null,
      "evidence": "Packed cell volume",
      "aliases": []
    },
    {
      "label": "Nursing Intervention",
      "definition": null,
      "synonyms": [],
      "provenance": [
        "schema_guided_completion",
        "symbolic_reasoner_dedupe"
      ],
      "stratum": "schema_guided",
      "original_label": null,
      "evidence": "Routine nursing care, physiotherapy, or bedside clinical activities",
      "aliases": []
    },
    {
      "label": "Routine Nursing Care",
      "definition": null,
      "synonyms": [],
      "provenance": [
        "schema_guided_completion",
        "symbolic_reasoner_dedupe"
      ],
      "stratum": "schema_guided",
      "original_label": null,
      "evidence": "Eye/mouth care, ET tube suction, bed care",
      "aliases": []
    },
    {
      "label": "Physiotherapy",
      "definition": null,
      "synonyms": [],
      "provenance": [
        "schema_guided_completion",
        "symbolic_reasoner_dedupe"
      ],
      "stratum": "schema_guided",
      "original_label": null,
      "evidence": "Physiotherapy sessions annotated in ICU management data",
      "aliases": []
    },
    {
      "label": "Bedside Intervention",
      "definition": null,
      "synonyms": [],
      "provenance": [
        "schema_guided_completion",
        "symbolic_reasoner_dedupe"
      ],
      "stratum": "schema_guided",
      "original_label": null,
      "evidence": "Line insertion/renewal, transducer calibration, x-ray",
      "aliases": []
    },
    {
      "label": "Patient Transport",
      "definition": null,
      "synonyms": [],
      "provenance": [
        "schema_guided_completion",
        "symbolic_reasoner_dedupe"
      ],
      "stratum": "schema_guided",
      "original_label": null,
      "evidence": "Transport to and from Theatre or CT-Scan",
      "aliases": []
    },
    {
      "label": "Sensor",
      "definition": null,
      "synonyms": [],
      "provenance": [
        "schema_guided_completion",
        "symbolic_reasoner_dedupe"
      ],
      "stratum": "schema_guided",
      "original_label": null,
      "evidence": "a machine or sensor used to record physiological parameters",
      "aliases": []
    },
    {
      "label": "Data Quality Assessment",
      "definition": null,
      "synonyms": [],
      "provenance": [
        "schema_guided_completion",
        "symbolic_reasoner_dedupe"
      ],
      "stratum": "schema_guided",
      "original_label": null,
      "evidence": "Automated evaluation of ICU data quality",
      "aliases": []
    }
  ],
  "relations": [
    {
      "label": "has outcome",
      "domain": "Patient",
      "range": "Outcome",
      "definition": null,
      "provenance": [
        "The BrainIT group concept and core dataset definition::chunk-0",
        "The BrainIT group concept and core dataset definition::chunk-13",
        "symbolic_reasoner_dedupe"
      ],
      "stratum": "core",
      "evidence": "assessing head injured patients' outcome from new therapies",
      "aliases": []
    },
    {
      "label": "has monitoring data",
      "domain": "Patient",
      "range": "Monitoring Data",
      "definition": null,
      "provenance": [
        "The BrainIT group concept and core dataset definition::chunk-0",
        "The BrainIT group concept and core dataset definition::chunk-1",
        "The BrainIT group concept and core dataset definition::chunk-6",
        "The BrainIT group concept and core dataset definition::chunk-13",
        "symbolic_reasoner_dedupe"
      ],
      "stratum": "core",
      "evidence": "more detailed collection of admission, monitoring, treatment and outcome data from patients with brain injury",
      "aliases": []
    },
    {
      "label": "targets condition",
      "domain": "Monitoring Data",
      "range": "Outcome",
      "definition": null,
      "provenance": [
        "The BrainIT group concept and core dataset definition::chunk-1",
        "symbolic_reasoner_dedupe"
      ],
      "stratum": "core",
      "evidence": "improving the care and outcome of brain-injured patients.",
      "aliases": []
    },
    {
      "label": "has clinical assessment",
      "domain": "Patient",
      "range": "GCS Assessment",
      "definition": null,
      "provenance": [
        "The BrainIT group concept and core dataset definition::chunk-7",
        "symbolic_reasoner_dedupe"
      ],
      "stratum": "core",
      "evidence": "the clinical status of the patient (e.g.: GCS scores)",
      "aliases": []
    },
    {
      "label": "has monitoring data",
      "domain": "Patient",
      "range": "Heart Rate",
      "definition": null,
      "provenance": [
        "The BrainIT group concept and core dataset definition::chunk-7",
        "symbolic_reasoner_dedupe"
      ],
      "stratum": "core",
      "evidence": "Minute by minute monitoring data... Heart Rate (specifying source: ECG or Pulse Oximetry)",
      "aliases": []
    },
    {
      "label": "has monitoring data",
      "domain": "Patient",
      "range": "Respiration Rate",
      "definition": null,
      "provenance": [
        "The BrainIT group concept and core dataset definition::chunk-7",
        "symbolic_reasoner_dedupe"
      ],
      "stratum": "core",
      "evidence": "Respiration Rate (sources: impedance plethmography or ventilator)",
      "aliases": []
    },
    {
      "label": "has monitoring data",
      "domain": "Patient",
      "range": "Mean Arterial Pressure (MAP)",
      "definition": null,
      "provenance": [
        "The BrainIT group concept and core dataset definition::chunk-7",
        "symbolic_reasoner_dedupe"
      ],
      "stratum": "core",
      "evidence": "Mean Arterial Pressure",
      "aliases": []
    },
    {
      "label": "has monitoring data",
      "domain": "Patient",
      "range": "SaO2",
      "definition": null,
      "provenance": [
        "The BrainIT group concept and core dataset definition::chunk-7",
        "symbolic_reasoner_dedupe"
      ],
      "stratum": "core",
      "evidence": "Pulse Oximetry (SaO2)",
      "aliases": []
    },
    {
      "label": "has monitoring data",
      "domain": "Patient",
      "range": "Temperature",
      "definition": null,
      "provenance": [
        "The BrainIT group concept and core dataset definition::chunk-7",
        "symbolic_reasoner_dedupe"
      ],
      "stratum": "core",
      "evidence": "Temperature (sources: rectal=oesophageal= bladder=skin)",
      "aliases": []
    },
    {
      "label": "has monitoring data",
      "domain": "Patient",
      "range": "CVP",
      "definition": null,
      "provenance": [
        "The BrainIT group concept and core dataset definition::chunk-7",
        "symbolic_reasoner_dedupe"
      ],
      "stratum": "core",
      "evidence": "Central Venous Pressure (CVP)",
      "aliases": []
    },
    {
      "label": "has monitoring data",
      "domain": "Patient",
      "range": "Brain Temperature",
      "definition": null,
      "provenance": [
        "The BrainIT group concept and core dataset definition::chunk-7",
        "symbolic_reasoner_dedupe"
      ],
      "stratum": "core",
      "evidence": "Brain Temperature",
      "aliases": []
    },
    {
      "label": "has monitoring data",
      "domain": "Patient",
      "range": "Microdialysis",
      "definition": null,
      "provenance": [
        "The BrainIT group concept and core dataset definition::chunk-7",
        "symbolic_reasoner_dedupe"
      ],
      "stratum": "core",
      "evidence": "Microdialysis",
      "aliases": []
    },
    {
      "label": "has clinical assessment",
      "domain": "Patient",
      "range": "Pupil Assessment",
      "definition": null,
      "provenance": [
        "The BrainIT group concept and core dataset definition::chunk-8",
        "symbolic_reasoner_dedupe"
      ],
      "stratum": "core",
      "evidence": "pupil scores",
      "aliases": []
    },
    {
      "label": "has laboratory value",
      "domain": "Patient",
      "range": "Biochemistry",
      "definition": null,
      "provenance": [
        "The BrainIT group concept and core dataset definition::chunk-8",
        "symbolic_reasoner_dedupe"
      ],
      "stratum": "core",
      "evidence": "Biochemistry (Na, K \u00fe , Glucose)",
      "aliases": []
    },
    {
      "label": "has laboratory value",
      "domain": "Patient",
      "range": "Haematology",
      "definition": null,
      "provenance": [
        "The BrainIT group concept and core dataset definition::chunk-8",
        "symbolic_reasoner_dedupe"
      ],
      "stratum": "core",
      "evidence": "Haematology (Haemaglobin, White Cell Count, Haematocrit)",
      "aliases": []
    },
    {
      "label": "has session",
      "domain": "Patient",
      "range": "Session",
      "definition": null,
      "provenance": [
        "schema_guided_completion",
        "symbolic_reasoner_dedupe"
      ],
      "stratum": "schema_guided",
      "evidence": "has been designed and is being tested",
      "aliases": []
    },
    {
      "label": "has clinical assessment",
      "domain": "Patient",
      "range": "Clinical Assessment",
      "definition": null,
      "provenance": [
        "schema_guided_completion",
        "symbolic_reasoner_dedupe"
      ],
      "stratum": "schema_guided",
      "evidence": "structured clinical evaluation performed at admission",
      "aliases": []
    },
    {
      "label": "has laboratory value",
      "domain": "Patient",
      "range": "Laboratory Values",
      "definition": null,
      "provenance": [
        "schema_guided_completion",
        "symbolic_reasoner_dedupe"
      ],
      "stratum": "schema_guided",
      "evidence": "Routine laboratory tests performed during ICU management",
      "aliases": []
    },
    {
      "label": "has nursing intervention",
      "domain": "Patient",
      "range": "Nursing Intervention",
      "definition": null,
      "provenance": [
        "schema_guided_completion",
        "symbolic_reasoner_dedupe"
      ],
      "stratum": "schema_guided",
      "evidence": "Routine nursing care, physiotherapy, or bedside clinical activities",
      "aliases": []
    },
    {
      "label": "has timepoint",
      "domain": "Session",
      "range": "Timepoint",
      "definition": null,
      "provenance": [
        "schema_guided_completion",
        "symbolic_reasoner_dedupe"
      ],
      "stratum": "schema_guided",
      "evidence": "Time of BP, ICP and central venous pressure (CVP) monitoring",
      "aliases": []
    },
    {
      "label": "has observation",
      "domain": "Timepoint",
      "range": "Observation",
      "definition": null,
      "provenance": [
        "schema_guided_completion",
        "symbolic_reasoner_dedupe"
      ],
      "stratum": "schema_guided",
      "evidence": "Time of BP, ICP and central venous pressure (CVP) monitoring",
      "aliases": []
    },
    {
      "label": "measures parameter",
      "domain": "Observation",
      "range": "Parameter",
      "definition": null,
      "provenance": [
        "schema_guided_completion",
        "symbolic_reasoner_dedupe"
      ],
      "stratum": "schema_guided",
      "evidence": "monitoring data was also performed",
      "aliases": []
    },
    {
      "label": "produced by sensor",
      "domain": "Observation",
      "range": "Sensor",
      "definition": null,
      "provenance": [
        "schema_guided_completion",
        "symbolic_reasoner_dedupe"
      ],
      "stratum": "schema_guided",
      "evidence": "a machine or sensor used to record physiological parameters",
      "aliases": []
    },
    {
      "label": "has quality assessment",
      "domain": "Observation",
      "range": "Data Quality Assessment",
      "definition": null,
      "provenance": [
        "schema_guided_completion",
        "symbolic_reasoner_dedupe"
      ],
      "stratum": "schema_guided",
      "evidence": "Automated evaluation of ICU data quality",
      "aliases": []
    }
  ],
  "hierarchy": [
    {
      "subClass": "Intracranial Hypertension",
      "superClass": "Secondary Insult",
      "evidence": "As a result, secondary insults such as intracranial hypertension, and arterial hypotension have been found to occur, in head injured patients, more frequently than previously realised with more than 90 percent of patients exhibiting one or more insults during their management in intensive care [12].",
      "provenance": [
        "The BrainIT group concept and core dataset definition::chunk-11"
      ],
      "stratum": "core"
    },
    {
      "subClass": "SjO2",
      "superClass": "Optional Monitoring Parameter",
      "evidence": "SjO2",
      "provenance": [
        "schema_guided_completion"
      ],
      "stratum": "schema_guided"
    },
    {
      "subClass": "EtCO2",
      "superClass": "Optional Monitoring Parameter",
      "evidence": "EtCO2",
      "provenance": [
        "schema_guided_completion"
      ],
      "stratum": "schema_guided"
    },
    {
      "subClass": "TCD",
      "superClass": "Optional Monitoring Parameter",
      "evidence": "TCD",
      "provenance": [
        "schema_guided_completion"
      ],
      "stratum": "schema_guided"
    },
    {
      "subClass": "PbrO2",
      "superClass": "Optional Monitoring Parameter",
      "evidence": "PbrO2",
      "provenance": [
        "schema_guided_completion"
      ],
      "stratum": "schema_guided"
    },
    {
      "subClass": "Cerebral Perfusion Pressure (CPP)",
      "superClass": "Derived Parameter",
      "evidence": "Cerebral perfusion pressure (CPP 1/4 BP-ICP) monitoring",
      "provenance": [
        "schema_guided_completion"
      ],
      "stratum": "schema_guided"
    },
    {
      "subClass": "Antibiotics",
      "superClass": "Baseline Therapy",
      "evidence": "antibiotics",
      "provenance": [
        "schema_guided_completion"
      ],
      "stratum": "schema_guided"
    },
    {
      "subClass": "Nutrition",
      "superClass": "Baseline Therapy",
      "evidence": "nutrition",
      "provenance": [
        "schema_guided_completion"
      ],
      "stratum": "schema_guided"
    },
    {
      "subClass": "Routine Nursing Care",
      "superClass": "Nursing Intervention",
      "evidence": "Eye/mouth care, ET tube suction, bed care",
      "provenance": [
        "schema_guided_completion"
      ],
      "stratum": "schema_guided"
    },
    {
      "subClass": "Physiotherapy",
      "superClass": "Nursing Intervention",
      "evidence": "Physiotherapy sessions annotated in ICU management data",
      "provenance": [
        "schema_guided_completion"
      ],
      "stratum": "schema_guided"
    },
    {
      "subClass": "Patient Transport",
      "superClass": "Nursing Intervention",
      "evidence": "Transport to and from Theatre or CT-Scan",
      "provenance": [
        "schema_guided_completion"
      ],
      "stratum": "schema_guided"
    },
    {
      "subClass": "Jugular Venous Desaturation",
      "superClass": "Secondary Insult",
      "evidence": "Schema-inferred: Jugular Venous Desaturation is a subclass of Secondary Insult.",
      "provenance": [
        "llm_reasoning_layer_patch"
      ],
      "stratum": "llm_reasoning",
      "justification": "Jugular Venous Desaturation is a type of Secondary Insult.",
      "confidence": 0.7
    },
    {
      "subClass": "Sedation",
      "superClass": "Baseline Therapy",
      "evidence": "Schema-inferred: Sedation is a subclass of Baseline Therapy.",
      "provenance": [
        "llm_reasoning_layer_patch"
      ],
      "stratum": "llm_reasoning",
      "justification": "Sedation is a type of Baseline Therapy.",
      "confidence": 0.7
    },
    {
      "subClass": "White Blood Cell Count",
      "superClass": "Haematology",
      "evidence": "Schema-inferred: White Blood Cell Count is a subclass of Haematology.",
      "provenance": [
        "llm_reasoning_layer_patch"
      ],
      "stratum": "llm_reasoning",
      "justification": "Sodium is a type of Biochemistry.",
      "confidence": 0.7
    },
    {
      "subClass": "Secondary Insult Treatment",
      "superClass": "Secondary Insult Therapy",
      "evidence": "Schema-inferred: Secondary Insult Treatment is a subclass of Secondary Insult Therapy.",
      "provenance": [
        "llm_reasoning_layer_patch"
      ],
      "stratum": "llm_reasoning",
      "justification": "Secondary Insult Treatment is a specific type of Secondary Insult Therapy.",
      "confidence": 0.7
    },
    {
      "subClass": "Potassium",
      "superClass": "Biochemistry",
      "evidence": "Schema-inferred: Potassium is a subclass of Biochemistry.",
      "provenance": [
        "llm_reasoning_layer_patch"
      ],
      "stratum": "llm_reasoning",
      "justification": "Potassium is a type of Biochemistry.",
      "confidence": 0.7
    },
    {
      "subClass": "Mean Arterial Pressure (MAP)",
      "superClass": "Core Monitoring Parameter",
      "evidence": "Schema-inferred: Mean Arterial Pressure (MAP) is a subclass of Core Monitoring Parameter.",
      "provenance": [
        "llm_reasoning_layer_patch"
      ],
      "stratum": "llm_reasoning",
      "justification": "Mean Arterial Pressure (MAP) is a Core Monitoring Parameter.",
      "confidence": 0.7
    },
    {
      "subClass": "Intracranial Pressure (ICP)",
      "superClass": "Core Monitoring Parameter",
      "evidence": "Schema-inferred: Intracranial Pressure (ICP) is a subclass of Core Monitoring Parameter.",
      "provenance": [
        "llm_reasoning_layer_patch"
      ],
      "stratum": "llm_reasoning",
      "justification": "Intracranial Pressure (ICP) is a Core Monitoring Parameter.",
      "confidence": 0.7
    },
    {
      "subClass": "CT Scan Assessment",
      "superClass": "Clinical Assessment",
      "evidence": "Schema-inferred: CT Scan Assessment is a subclass of Clinical Assessment.",
      "provenance": [
        "llm_reasoning_layer_patch"
      ],
      "stratum": "llm_reasoning",
      "justification": "CT Scan Assessment is a Clinical Assessment.",
      "confidence": 0.7
    },
    {
      "subClass": "Possible Error",
      "superClass": "Data Quality Assessment",
      "evidence": "Schema-inferred: Possible Error is a subclass of Data Quality Assessment.",
      "provenance": [
        "llm_reasoning_layer_patch"
      ],
      "stratum": "llm_reasoning",
      "justification": "Possible Error is a type of Data Quality Assessment.",
      "confidence": 0.7
    },
    {
      "subClass": "Biochemistry",
      "superClass": "Laboratory Values",
      "evidence": "Schema-inferred: Biochemistry is a subclass of Laboratory Values.",
      "provenance": [
        "llm_reasoning_layer_patch"
      ],
      "stratum": "llm_reasoning",
      "justification": "Biochemistry is a type of Laboratory Values.",
      "confidence": 0.7
    },
    {
      "subClass": "Secondary Insult",
      "superClass": "Condition",
      "evidence": "Schema-inferred: Secondary Insult is a subclass of Condition.",
      "provenance": [
        "llm_reasoning_layer_patch"
      ],
      "stratum": "llm_reasoning",
      "justification": "Secondary Insult is a condition that affects patient outcomes.",
      "confidence": 0.7
    },
    {
      "subClass": "Haematology",
      "superClass": "Laboratory Values",
      "evidence": "Schema-inferred: Haematology is a subclass of Laboratory Values.",
      "provenance": [
        "llm_reasoning_layer_patch"
      ],
      "stratum": "llm_reasoning",
      "justification": "Haematology is a type of Laboratory Values.",
      "confidence": 0.7
    },
    {
      "subClass": "Pupil Assessment",
      "superClass": "Clinical Assessment",
      "evidence": "Schema-inferred: Pupil Assessment is a subclass of Clinical Assessment.",
      "provenance": [
        "llm_reasoning_layer_patch"
      ],
      "stratum": "llm_reasoning",
      "justification": "Pupil Assessment is a Clinical Assessment.",
      "confidence": 0.7
    },
    {
      "subClass": "Respiration Rate",
      "superClass": "Core Monitoring Parameter",
      "evidence": "Schema-inferred: Respiration Rate is a subclass of Core Monitoring Parameter.",
      "provenance": [
        "llm_reasoning_layer_patch"
      ],
      "stratum": "llm_reasoning",
      "justification": "Respiration Rate is a Core Monitoring Parameter.",
      "confidence": 0.7
    },
    {
      "subClass": "Fluids",
      "superClass": "Baseline Therapy",
      "evidence": "Schema-inferred: Fluids is a subclass of Baseline Therapy.",
      "provenance": [
        "llm_reasoning_layer_patch"
      ],
      "stratum": "llm_reasoning",
      "justification": "Fluids is a type of Baseline Therapy.",
      "confidence": 0.7
    },
    {
      "subClass": "Microdialysis",
      "superClass": "Optional Monitoring Parameter",
      "evidence": "Schema-inferred: Microdialysis is a subclass of Optional Monitoring Parameter.",
      "provenance": [
        "llm_reasoning_layer_patch"
      ],
      "stratum": "llm_reasoning",
      "justification": "Brain Temperature is an Optional Monitoring Parameter.",
      "confidence": 0.7
    },
    {
      "subClass": "Arterial Hypotension",
      "superClass": "Systemic Hypotension",
      "evidence": "Schema-inferred: Arterial Hypotension is a subclass of Systemic Hypotension.",
      "provenance": [
        "llm_reasoning_layer_patch"
      ],
      "stratum": "llm_reasoning",
      "justification": "Arterial Hypotension is a type of Systemic Hypotension.",
      "confidence": 0.7
    },
    {
      "subClass": "Hypotension",
      "superClass": "Condition",
      "evidence": "Schema-inferred: Hypotension is a subclass of Condition.",
      "provenance": [
        "llm_reasoning_layer_patch"
      ],
      "stratum": "llm_reasoning",
      "justification": "Hypotension is a condition that affects patient outcomes.",
      "confidence": 0.7
    },
    {
      "subClass": "GCS Assessment",
      "superClass": "Clinical Assessment",
      "evidence": "Schema-inferred: GCS Assessment is a subclass of Clinical Assessment.",
      "provenance": [
        "llm_reasoning_layer_patch"
      ],
      "stratum": "llm_reasoning",
      "justification": "GCS Assessment is a Clinical Assessment.",
      "confidence": 0.7
    },
    {
      "subClass": "Temperature",
      "superClass": "Core Monitoring Parameter",
      "evidence": "Schema-inferred: Temperature is a subclass of Core Monitoring Parameter.",
      "provenance": [
        "llm_reasoning_layer_patch"
      ],
      "stratum": "llm_reasoning",
      "justification": "Temperature is a Core Monitoring Parameter.",
      "confidence": 0.7
    },
    {
      "subClass": "Ventilation",
      "superClass": "Baseline Therapy",
      "evidence": "Schema-inferred: Ventilation is a subclass of Baseline Therapy.",
      "provenance": [
        "llm_reasoning_layer_patch"
      ],
      "stratum": "llm_reasoning",
      "justification": "Ventilation is a type of Baseline Therapy.",
      "confidence": 0.7
    },
    {
      "subClass": "Derived Parameter",
      "superClass": "Monitoring Data",
      "evidence": "Schema-inferred: Derived Parameter is a subclass of Monitoring Data.",
      "provenance": [
        "llm_reasoning_layer_patch"
      ],
      "stratum": "llm_reasoning",
      "justification": "Derived Parameter is a type of Monitoring Data.",
      "confidence": 0.7
    },
    {
      "subClass": "Vasopressors",
      "superClass": "Baseline Therapy",
      "evidence": "Schema-inferred: Vasopressors is a subclass of Baseline Therapy.",
      "provenance": [
        "llm_reasoning_layer_patch"
      ],
      "stratum": "llm_reasoning",
      "justification": "Arterial Pressors is a type of Baseline Therapy.",
      "confidence": 0.7
    },
    {
      "subClass": "Sepsis",
      "superClass": "Condition",
      "evidence": "Schema-inferred: Sepsis is a subclass of Condition.",
      "provenance": [
        "llm_reasoning_layer_patch"
      ],
      "stratum": "llm_reasoning",
      "justification": "Sepsis is a condition that impacts patient outcomes.",
      "confidence": 0.7
    },
    {
      "subClass": "GOSe Outcome",
      "superClass": "Outcome",
      "evidence": "Schema-inferred: GOSe Outcome is a subclass of Outcome.",
      "provenance": [
        "llm_reasoning_layer_patch"
      ],
      "stratum": "llm_reasoning",
      "justification": "GOSe Outcome is a type of Outcome.",
      "confidence": 0.7
    },
    {
      "subClass": "Sodium",
      "superClass": "Biochemistry",
      "evidence": "Schema-inferred: Sodium is a subclass of Biochemistry.",
      "provenance": [
        "symbolic_reasoner_subclass_completion"
      ]
    },
    {
      "subClass": "Hypertension",
      "superClass": "Condition",
      "evidence": "Schema-inferred: Hypertension is a subclass of Condition.",
      "provenance": [
        "symbolic_reasoner_subclass_completion"
      ]
    },
    {
      "subClass": "Blood Gases",
      "superClass": "Laboratory Values",
      "evidence": "Schema-inferred: Blood Gases is a subclass of Laboratory Values.",
      "provenance": [
        "symbolic_reasoner_subclass_completion"
      ]
    },
    {
      "subClass": "Acute Respiratory Distress Syndrome",
      "superClass": "Secondary Insult",
      "evidence": "Schema-inferred: Acute Respiratory Distress Syndrome is a subclass of Secondary Insult.",
      "provenance": [
        "symbolic_reasoner_subclass_completion"
      ]
    },
    {
      "subClass": "Core Monitoring Parameter",
      "superClass": "Monitoring Data",
      "evidence": "Schema-inferred: Core Monitoring Parameter is a subclass of Monitoring Data.",
      "provenance": [
        "symbolic_reasoner_subclass_completion"
      ]
    },
    {
      "subClass": "Glucose",
      "superClass": "Biochemistry",
      "evidence": "Schema-inferred: Glucose is a subclass of Biochemistry.",
      "provenance": [
        "symbolic_reasoner_subclass_completion"
      ]
    },
    {
      "subClass": "Bedside Intervention",
      "superClass": "Nursing Intervention",
      "evidence": "Schema-inferred: Bedside Intervention is a subclass of Nursing Intervention.",
      "provenance": [
        "symbolic_reasoner_subclass_completion"
      ]
    },
    {
      "subClass": "Systemic Hypotension",
      "superClass": "Secondary Insult",
      "evidence": "Schema-inferred: Systemic Hypotension is a subclass of Secondary Insult.",
      "provenance": [
        "symbolic_reasoner_subclass_completion"
      ]
    },
    {
      "subClass": "Brain Temperature",
      "superClass": "Optional Monitoring Parameter",
      "evidence": "Schema-inferred: Brain Temperature is a subclass of Optional Monitoring Parameter.",
      "provenance": [
        "symbolic_reasoner_subclass_completion"
      ]
    },
    {
      "subClass": "Heart Rate",
      "superClass": "Core Monitoring Parameter",
      "evidence": "Schema-inferred: Heart Rate is a subclass of Core Monitoring Parameter.",
      "provenance": [
        "symbolic_reasoner_subclass_completion"
      ]
    },
    {
      "subClass": "CVP",
      "superClass": "Optional Monitoring Parameter",
      "evidence": "Schema-inferred: CVP is a subclass of Optional Monitoring Parameter.",
      "provenance": [
        "symbolic_reasoner_subclass_completion"
      ]
    },
    {
      "subClass": "Adrenaline",
      "superClass": "Vasopressors",
      "evidence": "Schema-inferred: Adrenaline is a subclass of Vasopressors.",
      "provenance": [
        "symbolic_reasoner_subclass_completion"
      ]
    },
    {
      "subClass": "Haemoglobin",
      "superClass": "Haematology",
      "evidence": "Schema-inferred: Haemoglobin is a subclass of Haematology.",
      "provenance": [
        "symbolic_reasoner_subclass_completion"
      ]
    },
    {
      "subClass": "Arterial Pressors",
      "superClass": "Secondary Insult Therapy",
      "evidence": "Schema-inferred: Arterial Pressors is a subclass of Secondary Insult Therapy.",
      "provenance": [
        "symbolic_reasoner_subclass_completion"
      ]
    },
    {
      "subClass": "Optional Monitoring Parameter",
      "superClass": "Monitoring Data",
      "evidence": "Schema-inferred: Optional Monitoring Parameter is a subclass of Monitoring Data.",
      "provenance": [
        "symbolic_reasoner_subclass_completion"
      ]
    },
    {
      "subClass": "Haematocrit",
      "superClass": "Haematology",
      "evidence": "Schema-inferred: Haematocrit is a subclass of Haematology.",
      "provenance": [
        "symbolic_reasoner_subclass_completion"
      ]
    },
    {
      "subClass": "Probable Error",
      "superClass": "Data Quality Assessment",
      "evidence": "Schema-inferred: Probable Error is a subclass of Data Quality Assessment.",
      "provenance": [
        "symbolic_reasoner_subclass_completion"
      ]
    },
    {
      "subClass": "SaO2",
      "superClass": "Core Monitoring Parameter",
      "evidence": "Schema-inferred: SaO2 is a subclass of Core Monitoring Parameter.",
      "provenance": [
        "symbolic_reasoner_subclass_completion"
      ]
    },
    {
      "subClass": "Noradrenaline",
      "superClass": "Vasopressors",
      "evidence": "Schema-inferred: Noradrenaline is a subclass of Vasopressors.",
      "provenance": [
        "symbolic_reasoner_subclass_completion"
      ]
    }
  ],
  "metadata": {
    "strategy": "ui-baseline"
  }
}